odoo/addons/pms_crm/README.rst
odoo/addons/pms_crm/__init__.py
odoo/addons/pms_crm/__manifest__.py
odoo/addons/pms_crm/i18n/es.po
odoo/addons/pms_crm/i18n/pms_crm.pot
odoo/addons/pms_crm/models/__init__.py
odoo/addons/pms_crm/models/crm_lead.py
odoo/addons/pms_crm/models/pms_property.py
odoo/addons/pms_crm/readme/CONTRIBUTORS.rst
odoo/addons/pms_crm/readme/DESCRIPTION.rst
odoo/addons/pms_crm/readme/USAGE.rst
odoo/addons/pms_crm/static/description/icon.png
odoo/addons/pms_crm/static/description/index.html
odoo/addons/pms_crm/views/crm_lead.xml
odoo/addons/pms_crm/views/pms_property.xml
odoo14_addon_pms_crm-14.0.1.0.1.dev2.dist-info/METADATA
odoo14_addon_pms_crm-14.0.1.0.1.dev2.dist-info/WHEEL
odoo14_addon_pms_crm-14.0.1.0.1.dev2.dist-info/top_level.txt
odoo14_addon_pms_crm-14.0.1.0.1.dev2.dist-info/RECORD
